Metadata-Version: 2.1
Name: tablipy
Version: 0.1.5
Summary: A library for working with tabular data
Home-page: https://github.com/mirolaukka/tablipy
Author: Miro Laukka
Author-email: mjlaukka@gmail.com
Classifier: Programming Language :: Python :: 3
Classifier: License :: OSI Approved :: MIT License
Requires-Python: >=3.6
License-File: LICENSE
